Workbook

Sheet Launch Checklist
A1: Launch Checklist
A2: Work top to bottom. Change Status to Done as you go; the summary at the top updates automatically. Yellow cells are yours to edit.
A3: Progress: | B3: =COUNTIF(E6:E28,"Done")&" of "&COUNTA(B6:B28)&" tasks done ("&TEXT(COUNTIF(E6:E28,"Done")/COUNTA(B6:B28),"0%")&")"
A5: Phase | B5: Task | C5: Owner | D5: Due | E5: Status | F5: Notes / link
A6: Week 1: Foundation | B6: Merge website to main and connect Cloudflare Pages; verify lonestarmobilesecurity.com loads | E6: Done
A7: Week 1: Foundation | B7: Set up business phone number and add it to js/config.js | E7: Not started
A8: Week 1: Foundation | B8: Create Cal.com event 'Lease Consultation' and paste link into js/config.js | E8: Not started
A9: Week 1: Foundation | B9: Enable Cloudflare Email Routing for info@lonestarmobilesecurity.com | E9: Not started
A10: Week 1: Foundation | B10: Install Barlow fonts; add email signature with banner | E10: Not started
A11: Week 1: Foundation | B11: Order business cards (250) and sell sheets (100) | E11: Not started
A12: Week 1: Foundation | B12: Order 2 jobsite signs per tower (aluminum + Coroplast) | E12: Not started
A13: Week 1: Foundation | B13: Confirm rebranded imagery use with the equipment manufacturer / reseller agreement | E13: Not started
A14: Week 2: Be findable | B14: Create Google Business Profile (service-area business), add photos, services, hours, booking link | E14: Not started
A15: Week 2: Be findable | B15: Create Facebook Page, Instagram, LinkedIn Company Page, X; upload covers and profile picture | E15: Not started
A16: Week 2: Be findable | B16: List on Yelp, Nextdoor Business, Bing Places, Apple Business Connect, Angi, Thumbtack | E16: Not started
A17: Week 2: Be findable | B17: Publish first 4 social posts (Intro, Pricing, 4K, Solar) using the caption calendar | E17: Not started
... A28: Ongoing | B28: Review KPI Tracker every Monday; adjust budget and outreach volume | E28: Not started
A30: Legend: yellow cells are for you to fill in (Owner, Due, Status, Notes). Status drop-down drives the progress line above.

Sheet KPI Tracker
A1: Weekly KPI Tracker
A2: Enter the yellow columns each Monday for the prior week. Gray columns are formulas. Row 6 is an example week; overwrite it with real numbers.
A5: Week starting | B5: Outreach touches | C5: Consultations booked | D5: Consultations held | E5: Proposals sent | F5: Leases signed | G5: Towers deployed (new) | H5: Active towers (total) | I5: Monitored sites | J5: Ad spend ($) | K5: Booking rate | L5: Close rate | M5: Cost per lease ($) | N5: MRR ($)
A6: 2026-09-07 | B6: 40 | C6: 5 | D6: 4 | E6: 3 | F6: 1 | G6: 1 | H6: 1 | I6: 1 | J6: 300 | K6: =IF(B6>0,C6/B6,"") | L6: =IF(D6>0,F6/D6,"") | M6: =IF(F6>0,J6/F6,"") | N6: =H6*Assumptions!$B$3+I6*Assumptions!$B$4
K7: =IF(B7>0,C7/B7,"") | L7: =IF(D7>0,F7/D7,"") | M7: =IF(F7>0,J7/F7,"") | N7: =H7*Assumptions!$B$3+I7*Assumptions!$B$4
K8: =IF(B8>0,C8/B8,"") | L8: =IF(D8>0,F8/D8,"") | M8: =IF(F8>0,J8/F8,"") | N8: =H8*Assumptions!$B$3+I8*Assumptions!$B$4
K9: =IF(B9>0,C9/B9,"") | L9: =IF(D9>0,F9/D9,"") | M9: =IF(F9>0,J9/F9,"") | N9: =H9*Assumptions!$B$3+I9*Assumptions!$B$4
K10: =IF(B10>0,C10/B10,"") | L10: =IF(D10>0,F10/D10,"") | M10: =IF(F10>0,J10/F10,"") | N10: =H10*Assumptions!$B$3+I10*Assumptions!$B$4
K11: =IF(B11>0,C11/B11,"") | L11: =IF(D11>0,F11/D11,"") | M11: =IF(F11>0,J11/F11,"") | N11: =H11*Assumptions!$B$3+I11*Assumptions!$B$4
K12: =IF(B12>0,C12/B12,"") | L12: =IF(D12>0,F12/D12,"") | M12: =IF(F12>0,J12/F12,"") | N12: =H12*Assumptions!$B$3+I12*Assumptions!$B$4
K13: =IF(B13>0,C13/B13,"") | L13: =IF(D13>0,F13/D13,"") | M13: =IF(F13>0,J13/F13,"") | N13: =H13*Assumptions!$B$3+I13*Assumptions!$B$4
K14: =IF(B14>0,C14/B14,"") | L14: =IF(D14>0,F14/D14,"") | M14: =IF(F14>0,J14/F14,"") | N14: =H14*Assumptions!$B$3+I14*Assumptions!$B$4
K15: =IF(B15>0,C15/B15,"") | L15: =IF(D15>0,F15/D15,"") | M15: =IF(F15>0,J15/F15,"") | N15: =H15*Assumptions!$B$3+I15*Assumptions!$B$4
K16: =IF(B16>0,C16/B16,"") | L16: =IF(D16>0,F16/D16,"") | M16: =IF(F16>0,J16/F16,"") | N16: =H16*Assumptions!$B$3+I16*Assumptions!$B$4
K17: =IF(B17>0,C17/B17,"") | L17: =IF(D17>0,F17/D17,"") | M17: =IF(F17>0,J17/F17,"") | N17: =H17*Assumptions!$B$3+I17*Assumptions!$B$4
K18: =IF(B18>0,C18/B18,"") | L18: =IF(D18>0,F18/D18,"") | M18: =IF(F18>0,J18/F18,"") | N18: =H18*Assumptions!$B$3+I18*Assumptions!$B$4
... K31: =IF(B31>0,C31/B31,"") | L31: =IF(D31>0,F31/D31,"") | M31: =IF(F31>0,J31/F31,"") | N31: =H31*Assumptions!$B$3+I31*Assumptions!$B$4
A33: Totals / averages | B33: =SUM(B6:B31) | C33: =SUM(C6:C31) | D33: =SUM(D6:D31) | E33: =SUM(E6:E31) | F33: =SUM(F6:F31) | G33: =SUM(G6:G31) | J33: =SUM(J6:J31) | K33: =IF(B33>0,C33/B33,"") | L33: =IF(D33>0,F33/D33,"") | M33: =IF(F33>0,J33/F33,"")
A35: Benchmarks to aim for in the first 90 days: booking rate 10% of outreach touches, close rate 35% of consultations held, cost per lease under $600 in paid channels. Source: Lonestar planning assumptions, adjust to your actuals.

Sheet Assumptions
A1: Assumptions
A2: Blue values are inputs used by the KPI Tracker formulas.
A3: Tower monthly rate ($) | B3: 750
A4: Monitoring monthly rate per site ($) | B4: 150
A5: Guard comparison: hourly rate ($) | B5: 25
A6: Guard hours per night | B6: 12
A7: Nights per month | B7: 30
A8: Guard monthly cost ($) | B8: =B5*B6*B7
A10: Break-even towers for a $1,500/mo ad budget | B10: =1500/(B3+B4)
A12: Source: pricing set by Lonestar Mobile Security (Sept 2026). Guard rate is a planning assumption; replace with a real quote from a Houston guard service.
